nameko_opentsdb/__init__.py
nameko_opentsdb/opentsdb_providers.py
nameko_opentsdb_py-0.0.2.dist-info/DESCRIPTION.rst
nameko_opentsdb_py-0.0.2.dist-info/METADATA
nameko_opentsdb_py-0.0.2.dist-info/RECORD
nameko_opentsdb_py-0.0.2.dist-info/WHEEL
nameko_opentsdb_py-0.0.2.dist-info/metadata.json
nameko_opentsdb_py-0.0.2.dist-info/top_level.txt
