Metadata-Version: 2.0
Name: nameko-opentsdb-py
Version: 0.0.2
Summary: OpenTSDB dependency for Nameko services
Home-page: https://github.com/fraglab/nameko-opentsdb-py
Author: Sergey Suglobov
Author-email: s.suglobov@gmail.com
License: UNKNOWN
Keywords: nameko,opentsdb,tsdb,metrics
Platform: UNKNOWN
Classifier: Development Status :: 4 - Beta
Classifier: Environment :: Console
Classifier: Intended Audience :: Developers
Classifier: License :: OSI Approved :: MIT License
Classifier: Natural Language :: English
Classifier: Operating System :: Microsoft :: Windows
Classifier: Operating System :: POSIX
Classifier: Programming Language :: Python :: 3.6
Classifier: Programming Language :: Python :: 3.5
Classifier: Programming Language :: Python :: 3 :: Only
Requires-Dist: nameko
Requires-Dist: opentsdb-py
Requires-Dist: setuptools
